iterminal/__init__.py
iterminal/__main__.py
iterminal/commands.py
iterminal/component.py
iterminal/console.py
iterminal/interpreter.py
iterminal/shell.py
iterminal/web/__init__.py
iterminal/web/jqconsole.py
iterminal/web/webusb.py
iterminal-0.0.1.dist-info/LICENSE
iterminal-0.0.1.dist-info/METADATA
iterminal-0.0.1.dist-info/WHEEL
iterminal-0.0.1.dist-info/top_level.txt
iterminal-0.0.1.dist-info/RECORD
