Metadata-Version: 2.1
Name: iterminal
Version: 0.0.1
Summary: A framework for making python-interactive tools
Home-page: https://github.com/pfrommerd/python-terminal
Author: Daniel Pfrommer
License: UNKNOWN
Project-URL: Source, https://github.com/pfrommerd/python-terminal/
Keywords: python
Platform: UNKNOWN
Classifier: Development Status :: 3 - Alpha
Classifier: Intended Audience :: Developers
Classifier: Topic :: Software Development :: Build Tools
Classifier: License :: OSI Approved :: MIT License
Classifier: Programming Language :: Python :: 3
Classifier: Programming Language :: Python :: 3.6
Classifier: Operating System :: OS Independent
Requires-Dist: setuptools
Provides-Extra: dev
Provides-Extra: test
